Workbook

Sheet Information Asset Register
A1: Asset ID | B1: Asset Name | C1: Description | D1: Category | E1: Owner | F1: Custodian | G1: Business Unit | H1: Data Classification | I1: Business Criticality | J1: Location | K1: Regulatory Relevance | L1: Dependencies | M1: Risk Level | N1: Review Date
A2: AST-001 | B2: Microsoft Active Directory | C2: Centralized identity, authentication, group policy, and access-control service for corporate users and systems. | D2: Software | E2: IT Infrastructure Manager | F2: Systems Administration Team | G2: Information Technology | H2: Confidential | I2: Critical | J2: NexusGuard HQ Data Center | K2: ISO 27001; HIPAA | L2: VMware Cluster; DNS; Core Network | M2: High | N2: 46402
A3: AST-002 | B3: Microsoft 365 Tenant | C3: Corporate email, Microsoft Teams, SharePoint Online, OneDrive, and Office productivity services. | D3: IT Service | E3: Head of IT | F3: Cloud Operations Team | G3: Enterprise Services | H3: Confidential | I3: Critical | J3: Microsoft Cloud | K3: ISO 27001; HIPAA; GDPR | L3: Microsoft Entra ID; Internet Connectivity | M3: High | N3: 46402
A4: AST-003 | B4: HR Employee Database | C4: Database containing employee personal information, payroll records, contracts, performance data, and benefits information. | D4: Data Asset | E4: Human Resources Director | F4: Database Administration Team | G4: Human Resources | H4: Restricted | I4: High | J4: NexusGuard HQ Data Center | K4: GDPR; HIPAA; Employment Law | L4: Microsoft SQL Server; Active Directory | M4: High | N4: 46402
A5: AST-004 | B5: Finance ERP System | C5: Enterprise financial management platform supporting general ledger, accounts payable, billing, budgeting, and financial reporting. | D5: Software | E5: Chief Financial Officer | F5: ERP Administration Team | G5: Finance | H5: Confidential | I5: Critical | J5: NexusGuard HQ Data Center | K5: SOX; PCI DSS; ISO 27001 | L5: Finance Database; Active Directory; Backup Service | M5: High | N5: 46402
A6: AST-005 | B6: Salesforce CRM | C6: Cloud-based customer relationship management platform containing customer contacts, sales opportunities, contracts, and support history. | D6: Software | E6: Sales Director | F6: CRM Administrator | G6: Sales and Marketing | H6: Confidential | I6: High | J6: Salesforce Cloud | K6: GDPR; ISO 27001 | L6: Microsoft 365; Internet Connectivity; SSO | M6: Medium | N6: 46402
A7: AST-006 | B7: Palo Alto Perimeter Firewall | C7: Next-generation firewall protecting the corporate network and controlling inbound, outbound, and inter-segment traffic. | D7: Hardware | E7: Network and Security Manager | F7: Network Operations Team | G7: Information Technology | H7: Internal | I7: Critical | J7: NexusGuard HQ Server Room | K7: PCI DSS; HIPAA; ISO 27001 | L7: ISP Links; Core Switches; SIEM Platform | M7: High | N7: 46402
A8: AST-007 | B8: Corporate VPN Gateway | C8: Secure remote-access service used by employees and approved third parties to connect to internal systems. | D8: Infrastructure | E8: Network and Security Manager | F8: Network Operations Team | G8: Information Technology | H8: Confidential | I8: Critical | J8: NexusGuard HQ Data Center | K8: HIPAA; PCI DSS; ISO 27001 | L8: Perimeter Firewall; Active Directory; MFA Service | M8: High | N8: 46402
A9: AST-008 | B9: VMware vSphere Cluster | C9: Virtualization platform hosting critical production, security, database, and business application servers. | D9: Infrastructure | E9: IT Infrastructure Manager | F9: Virtualization Team | G9: Information Technology | H9: Internal | I9: Critical | J9: NexusGuard HQ Data Center | K9: ISO 27001; HIPAA; PCI DSS | L9: SAN Storage; Core Network; Backup Service | M9: High | N9: 46402
A10: AST-009 | B10: Veeam Backup Repository | C10: Central repository storing encrypted backups of production servers, databases, file shares, and cloud workloads. | D10: Data Asset | E10: IT Operations Manager | F10: Backup and Recovery Team | G10: Information Technology | H10: Restricted | I10: Critical | J10: NexusGuard Disaster Recovery Site | K10: HIPAA; PCI DSS; ISO 27001 | L10: Veeam Backup Server; Storage Array; WAN Link | M10: High | N10: 46402
A11: AST-010 | B11: Microsoft Sentinel SIEM | C11: Cloud security information and event management platform used for centralized logging, threat detection, alerting, and incident investigation. | D11: Software | E11: Security Operations Center Manager | F11: SOC Analysts | G11: Cybersecurity | H11: Confidential | I11: High | J11: Microsoft Azure Cloud | K11: HIPAA; PCI DSS; ISO 27001 | L11: Log Sources; Microsoft Entra ID; Internet Connectivity | M11: High | N11: 46402
A12: AST-011 | B12: Microsoft Defender for Endpoint | C12: Endpoint detection and response platform protecting corporate laptops, workstations, and servers from malware and advanced threats. | D12: Software | E12: Security Operations Center Manager | F12: Endpoint Management Team | G12: Cybersecurity | H12: Confidential | I12: High | J12: Microsoft Cloud | K12: HIPAA; PCI DSS; ISO 27001 | L12: Corporate Endpoints; Microsoft Entra ID; SIEM Platform | M12: Medium | N12: 46402
A13: AST-012 | B13: Cisco Catalyst Core Switch Stack | C13: Core switching infrastructure connecting servers, network segments, wireless services, firewalls, and internet gateways. | D13: Hardware | E13: Network and Security Manager | F13: Network Operations Team | G13: Information Technology | H13: Internal | I13: Critical | J13: NexusGuard HQ Server Room | K13: ISO 27001; PCI DSS | L13: Perimeter Firewall; Access Switches; UPS | M13: High | N13: 46402
... A46: AST-045 | B46: PayStream Corporate Email Tenant | C46: Separate Microsoft 365 tenant used by PayStream staff for email and collaboration until tenant consolidation. | D46: IT Service | E46: PayStream IT Lead | F46: PayStream IT Team | G46: PayStream Analytics | H46: Confidential | I46: High | J46: Microsoft Cloud | K46: ISO 27001; GDPR | L46: Microsoft Entra ID; Internet Connectivity; Microsoft 365 Tenant | M46: Medium | N46: 46371

Sheet Classification Guide
A1: Data Classification | B1: Definition | C1: Business Criticality | D1: Definition
A2: Public | B2: Approved for unrestricted public release. | C2: Low | D2: Loss or unavailability causes minimal operational impact.
A3: Internal | B3: For NexusGuard personnel and authorized third parties; unauthorized disclosure causes limited harm. | C3: Medium | D3: Disruption affects a business process but workarounds are available.
A4: Confidential | B4: Sensitive business, customer, security, or employee information requiring controlled access. | C4: High | D4: Disruption causes major operational, financial, contractual, or reputational impact.
A5: Restricted | B5: Highly sensitive or regulated information requiring the strongest access and handling controls. | C5: Critical | D5: Loss or unavailability stops essential operations or creates severe regulatory or safety impact.
A7: Risk Level | B7: Guidance
A8: Low | B8: Adequate controls are in place and residual impact and likelihood are limited.
A9: Medium | B9: Additional monitoring or planned treatment is required.
A10: High | B10: Immediate management attention and formal risk treatment are required.

Sheet IAR Summary
A1: NexusGuard Information Asset Register: Summary
A2: All counts are formulas over the Information Asset Register sheet (rows 2 to 46). Extend the ranges if assets are added below row 46.
A4: Key metric | B4: Value
A5: Total assets registered | B5: =COUNTA('Information Asset Register'!$B$2:$B$46) -> 45
A6: PayStream Analytics assets | B6: =COUNTIF('Information Asset Register'!$G$2:$G$46,"PayStream Analytics") -> 8
A7: Assets rated High risk | B7: =COUNTIF('Information Asset Register'!$M$2:$M$46,"High") -> 27
A8: Restricted and Critical assets | B8: =COUNTIFS('Information Asset Register'!$H$2:$H$46,"Restricted",'Information Asset Register'!$I$2:$I$46,"Critical") -> 12
A9: Critical assets rated High risk | B9: =COUNTIFS('Information Asset Register'!$I$2:$I$46,"Critical",'Information Asset Register'!$M$2:$M$46,"High") -> 23
A11: Category | B11: Assets | C11: % of register
A12: Software | B12: =COUNTIF('Information Asset Register'!$D$2:$D$46,A12) -> 12 | C12: =B12/$B$5 -> 0.26666667
A13: Hardware | B13: =COUNTIF('Information Asset Register'!$D$2:$D$46,A13) -> 7 | C13: =B13/$B$5 -> 0.15555556
A14: Data Asset | B14: =COUNTIF('Information Asset Register'!$D$2:$D$46,A14) -> 7 | C14: =B14/$B$5 -> 0.15555556
A15: Infrastructure | B15: =COUNTIF('Information Asset Register'!$D$2:$D$46,A15) -> 8 | C15: =B15/$B$5 -> 0.17777778
A16: Facility | B16: =COUNTIF('Information Asset Register'!$D$2:$D$46,A16) -> 5 | C16: =B16/$B$5 -> 0.11111111
A17: IT Service | B17: =COUNTIF('Information Asset Register'!$D$2:$D$46,A17) -> 6 | C17: =B17/$B$5 -> 0.13333333
A18: Total | B18: =SUM(B12:B17) -> 45 | C18: =B18/$B$5 -> 1
A20: Data Classification | B20: Assets | C20: % of register
A21: Public | B21: =COUNTIF('Information Asset Register'!$H$2:$H$46,A21) -> 0 | C21: =B21/$B$5 -> 0
A22: Internal | B22: =COUNTIF('Information Asset Register'!$H$2:$H$46,A22) -> 14 | C22: =B22/$B$5 -> 0.31111111
A23: Confidential | B23: =COUNTIF('Information Asset Register'!$H$2:$H$46,A23) -> 18 | C23: =B23/$B$5 -> 0.4
A24: Restricted | B24: =COUNTIF('Information Asset Register'!$H$2:$H$46,A24) -> 13 | C24: =B24/$B$5 -> 0.28888889
A25: Total | B25: =SUM(B21:B24) -> 45 | C25: =B25/$B$5 -> 1
A27: Business Criticality | B27: Assets | C27: % of register
A28: Low | B28: =COUNTIF('Information Asset Register'!$I$2:$I$46,A28) -> 0 | C28: =B28/$B$5 -> 0
A29: Medium | B29: =COUNTIF('Information Asset Register'!$I$2:$I$46,A29) -> 4 | C29: =B29/$B$5 -> 0.088888889
A30: High | B30: =COUNTIF('Information Asset Register'!$I$2:$I$46,A30) -> 13 | C30: =B30/$B$5 -> 0.28888889
A31: Critical | B31: =COUNTIF('Information Asset Register'!$I$2:$I$46,A31) -> 28 | C31: =B31/$B$5 -> 0.62222222
A32: Total | B32: =SUM(B28:B31) -> 45 | C32: =B32/$B$5 -> 1
A34: Risk Level | B34: Assets | C34: % of register
A35: Low | B35: =COUNTIF('Information Asset Register'!$M$2:$M$46,A35) -> 1 | C35: =B35/$B$5 -> 0.022222222
A36: Medium | B36: =COUNTIF('Information Asset Register'!$M$2:$M$46,A36) -> 17 | C36: =B36/$B$5 -> 0.37777778
A37: High | B37: =COUNTIF('Information Asset Register'!$M$2:$M$46,A37) -> 27 | C37: =B37/$B$5 -> 0.6
A38: Total | B38: =SUM(B35:B37) -> 45 | C38: =B38/$B$5 -> 1
A40: Classification vs Criticality (asset count) | B40: Low | C40: Medium | D40: High | E40: Critical
A41: Public | B41: =COUNTIFS('Information Asset Register'!$H$2:$H$46,$A41,'Information Asset Register'!$I$2:$I$46,B$40) -> 0 | C41: =COUNTIFS('Information Asset Register'!$H$2:$H$46,$A41,'Information Asset Register'!$I$2:$I$46,C$40) -> 0 | D41: =COUNTIFS('Information Asset Register'!$H$2:$H$46,$A41,'Information Asset Register'!$I$2:$I$46,D$40) -> 0 | E41: =COUNTIFS('Information Asset Register'!$H$2:$H$46,$A41,'Information Asset Register'!$I$2:$I$46,E$40) -> 0
A42: Internal | B42: =COUNTIFS('Information Asset Register'!$H$2:$H$46,$A42,'Information Asset Register'!$I$2:$I$46,B$40) -> 0 | C42: =COUNTIFS('Information Asset Register'!$H$2:$H$46,$A42,'Information Asset Register'!$I$2:$I$46,C$40) -> 4 | D42: =COUNTIFS('Information Asset Register'!$H$2:$H$46,$A42,'Information Asset Register'!$I$2:$I$46,D$40) -> 1 | E42: =COUNTIFS('Information Asset Register'!$H$2:$H$46,$A42,'Information Asset Register'!$I$2:$I$46,E$40) -> 9
A43: Confidential | B43: =COUNTIFS('Information Asset Register'!$H$2:$H$46,$A43,'Information Asset Register'!$I$2:$I$46,B$40) -> 0 | C43: =COUNTIFS('Information Asset Register'!$H$2:$H$46,$A43,'Information Asset Register'!$I$2:$I$46,C$40) -> 0 | D43: =COUNTIFS('Information Asset Register'!$H$2:$H$46,$A43,'Information Asset Register'!$I$2:$I$46,D$40) -> 11 | E43: =COUNTIFS('Information Asset Register'!$H$2:$H$46,$A43,'Information Asset Register'!$I$2:$I$46,E$40) -> 7
A44: Restricted | B44: =COUNTIFS('Information Asset Register'!$H$2:$H$46,$A44,'Information Asset Register'!$I$2:$I$46,B$40) -> 0 | C44: =COUNTIFS('Information Asset Register'!$H$2:$H$46,$A44,'Information Asset Register'!$I$2:$I$46,C$40) -> 0 | D44: =COUNTIFS('Information Asset Register'!$H$2:$H$46,$A44,'Information Asset Register'!$I$2:$I$46,D$40) -> 1 | E44: =COUNTIFS('Information Asset Register'!$H$2:$H$46,$A44,'Information Asset Register'!$I$2:$I$46,E$40) -> 12

Sheet Document Control
B2: Document Control
B4: Item | C4: Description
B5: Document Title | C5: Information Asset Register (IAR)
B6: Doc Ref. | C6: IAR-001
B7: Classification | C7: Internal
B8: Status | C8: Draft for ISSC review
B9: Release Date | C9: 12/10/2026
B10: Owner | C10: Chief Information Security Officer (CISO)
B11: Prepared by | C11: Augustine Ozor, GRC Analyst
B12: Requested by | C12: Michael Chen
B13: Next Review Date | C13: 12 months from approval, or sooner on material change or acquisition
B15: Version History
B16: Version No. | C16: Date | D16: Author(s) | E16: Remarks
B17: 1.0 | C17: 12/10/2026 | D17: Augustine Ozor | E17: Register expanded from 15 to 45 assets, including 8 provisional PayStream Analytics assets.
B19: Notes
B20: PayStream entries (AST-038 to AST-045) are provisional: they were built from the acquisition documentation and must be validated against PayStream asset discovery before the next review.
B21: Review Date means the next scheduled review. PayStream assets are set earlier (15/12/2026) because integration is unfinished.
B22: Risk Level follows the Classification Guide. Ratings are initial judgments pending formal risk assessment.
